AUTHORS.rst
CHANGELOG.rst
LICENSE
MANIFEST.in
README.rst
setup.cfg
setup.py
src/timelog2csv.py
src/timelog2csv.egg-info/PKG-INFO
src/timelog2csv.egg-info/SOURCES.txt
src/timelog2csv.egg-info/dependency_links.txt
src/timelog2csv.egg-info/entry_points.txt
src/timelog2csv.egg-info/not-zip-safe
src/timelog2csv.egg-info/requires.txt
src/timelog2csv.egg-info/top_level.txt