Metadata-Version: 1.1
Name: timelog2csv
Version: 0.1.1
Summary: Converts a TimeLog calendar to a CSV file.
Home-page: https://bitbucket.org/keimlink/timelog2csv
Author: Markus Zapke-Gründemann
Author-email: markus@keimlink.de
License: BSD
Keywords: timelog2csv timelog csv
Platform: UNKNOWN
Classifier: Development Status :: 4 - Beta
Classifier: Environment :: Console
Classifier: Intended Audience :: Developers
Classifier: License :: OSI Approved :: BSD License
Classifier: Natural Language :: English
Classifier: Operating System :: OS Independent
Classifier: Programming Language :: Python :: 2
Classifier: Programming Language :: Python :: 2.6
Classifier: Programming Language :: Python :: 2.7
Classifier: Topic :: Utilities
